suno/__init__.py
suno/notebook_helpers.py
suno-0.0.1a0.dist-info/METADATA
suno-0.0.1a0.dist-info/WHEEL
suno-0.0.1a0.dist-info/top_level.txt
suno-0.0.1a0.dist-info/RECORD
