Metadata-Version: 2.1
Name: suno
Version: 0.0.1a0
Summary: Suno audio tools.
Home-page: UNKNOWN
Author: suno.ai
License: UNKNOWN
Platform: UNKNOWN
